{"drivers": {"8": {"name": "Kimi R\u00e4ikk\u00f6nen", "constructor": "Alfa Romeo", "color": "#960000"}, "841": {"name": "Antonio Giovinazzi", "constructor": "Alfa Romeo", "color": "#960000"}, "842": {"name": "Pierre Gasly", "constructor": "AlphaTauri", "color": "#C8C8C8"}, "826": {"name": "Daniil Kvyat", "constructor": "AlphaTauri", "color": "#C8C8C8"}, "20": {"name": "Sebastian Vettel", "constructor": "Ferrari", "color": "#C00000"}, "844": {"name": "Charles Leclerc", "constructor": "Ferrari", "color": "#C00000"}, "154": {"name": "Romain Grosjean", "constructor": "Haas F1 Team", "color": "#787878"}, "825": {"name": "Kevin Magnussen", "constructor": "Haas F1 Team", "color": "#787878"}, "846": {"name": "Lando Norris", "constructor": "McLaren", "color": "#FF8700"}, "832": {"name": "Carlos Sainz", "constructor": "McLaren", "color": "#FF8700"}, "1": {"name": "Lewis Hamilton", "constructor": "Mercedes", "color": "#00D2BE"}, "822": {"name": "Valtteri Bottas", "constructor": "Mercedes", "color": "#00D2BE"}, "815": {"name": "Sergio P\u00e9rez", "constructor": "Racing Point", "color": "#F596C8"}, "840": {"name": "Lance Stroll", "constructor": "Racing Point", "color": "#F596C8"}, "848": {"name": "Alexander Albon", "constructor": "Red Bull", "color": "#0600EF"}, "830": {"name": "Max Verstappen", "constructor": "Red Bull", "color": "#0600EF"}, "817": {"name": "Daniel Ricciardo", "constructor": "Renault", "color": "#FFF500"}, "839": {"name": "Esteban Ocon", "constructor": "Renault", "color": "#FFF500"}, "849": {"name": "Nicholas Latifi", "constructor": "Williams", "color": "#0082FA"}, "847": {"name": "George Russell", "constructor": "Williams", "color": "#0082FA"}}, "name": "Tuscan Grand Prix", "year": 2020, "order": [1, 822, 830, 848, 815, 832, 846, 840, 817, 844, 839, 842, 20, 826, 825, 154, 847, 8, 841, 849], "predictions": {"8": {"15": 1601, "13": 905, "18": 1354, "17": 1697, "16": 2093, "19": 619, "14": 1155, "12": 429, "11": 112, "10": 30, "7": 1, "9": 1, "8": 3}, "841": {"18": 2005, "19": 1808, "17": 2173, "16": 1674, "12": 134, "11": 29, "15": 1306, "13": 370, "14": 494, "10": 3, "8": 3, "9": 1}, "842": {"6": 790, "12": 831, "7": 1191, "10": 1672, "19": 196, "9": 964, "5": 557, "8": 1425, "11": 1300, "14": 233, "18": 72, "2": 87, "4": 311, "3": 208, "13": 134, "17": 13, "15": 6, "1": 9, "16": 1}, "826": {"12": 1848, "13": 1305, "7": 391, "6": 208, "9": 1140, "11": 1953, "8": 737, "10": 1517, "2": 2, "19": 220, "3": 16, "5": 93, "14": 345, "18": 65, "4": 47, "16": 22, "15": 82, "17": 9}, "20": {"9": 1324, "6": 274, "12": 1531, "8": 808, "14": 478, "2": 85, "13": 1373, "11": 1279, "15": 304, "3": 185, "10": 923, "5": 212, "19": 264, "16": 113, "4": 189, "0": 3, "17": 80, "7": 469, "18": 90, "1": 16}, "844": {"14": 298, "4": 451, "9": 993, "12": 1171, "7": 826, "10": 1045, "3": 469, "19": 217, "6": 597, "8": 1274, "13": 303, "16": 30, "11": 1194, "5": 495, "17": 26, "18": 74, "1": 71, "2": 387, "0": 14, "15": 65}, "154": {"17": 1292, "18": 871, "13": 1292, "15": 2045, "16": 1492, "14": 1436, "11": 213, "10": 47, "12": 614, "19": 685, "9": 8, "6": 1, "8": 4}, "825": {"16": 1509, "17": 1201, "18": 896, "12": 603, "15": 2080, "13": 1363, "14": 1417, "19": 659, "11": 192, "10": 60, "9": 16, "8": 2, "7": 2}, "846": {"8": 581, "2": 406, "11": 196, "19": 193, "6": 1526, "9": 487, "5": 1812, "4": 1649, "3": 1033, "10": 392, "7": 1188, "13": 86, "14": 239, "12": 84, "18": 81, "1": 36, "0": 2, "16": 1, "17": 7, "15": 1}, "832": {"7": 865, "3": 1443, "2": 607, "11": 154, "8": 487, "4": 1908, "5": 1690, "6": 1456, "9": 342, "18": 95, "19": 228, "10": 278, "14": 210, "13": 75, "12": 55, "0": 2, "1": 82, "16": 4, "17": 19}, "1": {"0": 7329, "19": 176, "1": 1741, "18": 105, "9": 226, "14": 172, "2": 39, "7": 6, "17": 29, "8": 73, "13": 68, "3": 7, "12": 15, "16": 8, "11": 2, "4": 2, "6": 2}, "822": {"1": 6437, "8": 49, "0": 2470, "19": 185, "18": 103, "9": 234, "17": 39, "3": 28, "13": 90, "14": 199, "2": 144, "12": 9, "7": 5, "10": 1, "16": 3, "4": 2, "11": 1, "5": 1}, "815": {"2": 1185, "9": 653, "3": 1238, "5": 937, "6": 997, "7": 833, "8": 767, "18": 95, "4": 1090, "11": 461, "10": 592, "1": 233, "14": 210, "12": 306, "19": 188, "13": 153, "0": 36, "17": 18, "15": 4, "16": 4}, "840": {"4": 1015, "1": 103, "10": 740, "3": 998, "9": 906, "8": 907, "6": 945, "5": 905, "2": 556, "7": 1060, "18": 79, "11": 602, "19": 227, "12": 430, "14": 245, "13": 245, "17": 10, "0": 17, "15": 8, "16": 2}, "848": {"5": 1564, "11": 158, "4": 1464, "2": 690, "3": 2605, "8": 400, "10": 240, "18": 82, "7": 737, "6": 965, "9": 423, "1": 75, "14": 240, "13": 78, "12": 69, "19": 189, "17": 16, "15": 1, "16": 2, "0": 2}, "830": {"3": 1098, "5": 250, "9": 255, "14": 219, "19": 184, "2": 5521, "1": 1145, "4": 811, "6": 97, "18": 85, "0": 122, "13": 81, "8": 52, "17": 21, "12": 11, "7": 38, "10": 6, "11": 2, "15": 1, "16": 1}, "817": {"10": 933, "7": 1375, "5": 1078, "4": 842, "12": 324, "3": 579, "14": 229, "8": 1280, "6": 1433, "11": 570, "9": 626, "2": 260, "19": 228, "1": 48, "18": 69, "13": 105, "0": 3, "15": 5, "17": 11, "16": 2}, "839": {"13": 570, "10": 1482, "8": 1144, "7": 1013, "14": 247, "11": 1422, "12": 944, "9": 1393, "6": 709, "19": 226, "5": 406, "4": 219, "18": 62, "2": 31, "16": 2, "3": 93, "1": 4, "15": 23, "17": 10}, "849": {"19": 2807, "16": 1182, "18": 2224, "13": 280, "15": 1041, "17": 1883, "14": 493, "12": 69, "11": 16, "9": 1, "10": 4}, "847": {"11": 144, "14": 1441, "19": 501, "17": 1446, "13": 1124, "18": 1493, "15": 1427, "16": 1855, "12": 523, "10": 35, "8": 4, "9": 7}}}