{"name": "Hungarian Grand Prix", "year": 2021, "drivers": {"8": {"name": "Kimi R\u00e4ikk\u00f6nen", "constructor": "Alfa Romeo", "color": "#900000"}, "841": {"name": "Antonio Giovinazzi", "constructor": "Alfa Romeo", "color": "#900000"}, "842": {"name": "Pierre Gasly", "constructor": "AlphaTauri", "color": "#2B4562"}, "852": {"name": "Yuki Tsunoda", "constructor": "AlphaTauri", "color": "#2B4562"}, "20": {"name": "Sebastian Vettel", "constructor": "Aston Martin", "color": "#006F62"}, "844": {"name": "Charles Leclerc", "constructor": "Ferrari", "color": "#DC0000"}, "853": {"name": "Nikita Mazepin", "constructor": "Haas F1 Team", "color": "#FFFFFF"}, "854": {"name": "Mick Schumacher", "constructor": "Haas F1 Team", "color": "#FFFFFF"}, "846": {"name": "Lando Norris", "constructor": "McLaren", "color": "#FF9800"}, "832": {"name": "Carlos Sainz", "constructor": "Ferrari", "color": "#DC0000"}, "1": {"name": "Lewis Hamilton", "constructor": "Mercedes", "color": "#00D2BE"}, "822": {"name": "Valtteri Bottas", "constructor": "Mercedes", "color": "#00D2BE"}, "815": {"name": "Sergio P\u00e9rez", "constructor": "Red Bull", "color": "#0600EF"}, "840": {"name": "Lance Stroll", "constructor": "Aston Martin", "color": "#006F62"}, "4": {"name": "Fernando Alonso", "constructor": "Alpine F1 Team", "color": "#0090FF"}, "830": {"name": "Max Verstappen", "constructor": "Red Bull", "color": "#0600EF"}, "817": {"name": "Daniel Ricciardo", "constructor": "McLaren", "color": "#FF9800"}, "839": {"name": "Esteban Ocon", "constructor": "Alpine F1 Team", "color": "#0090FF"}, "849": {"name": "Nicholas Latifi", "constructor": "Williams", "color": "#005AFF"}, "847": {"name": "George Russell", "constructor": "Williams", "color": "#005AFF"}}, "order": [830, 1, 822, 815, 846, 844, 842, 832, 817, 840, 852, 20, 4, 839, 847, 841, 8, 849, 854, 853], "predictions": {"8": {"16": 3550, "17": 2612, "15": 2047, "14": 737, "19": 294, "12": 157, "13": 421, "18": 106, "8": 5, "9": 6, "11": 45, "10": 20}, "841": {"15": 2788, "10": 344, "13": 1679, "16": 1114, "11": 549, "7": 49, "12": 972, "14": 1786, "9": 271, "18": 51, "8": 118, "19": 248, "17": 19, "6": 8, "5": 3, "4": 1}, "842": {"4": 1203, "2": 400, "5": 1182, "7": 1227, "1": 216, "14": 278, "0": 180, "8": 1080, "6": 1313, "18": 72, "12": 247, "3": 793, "10": 499, "19": 219, "9": 550, "13": 172, "11": 321, "15": 24, "16": 8, "17": 16}, "852": {"6": 397, "7": 692, "8": 945, "9": 1477, "13": 1091, "11": 928, "5": 243, "19": 253, "10": 852, "14": 899, "15": 547, "17": 128, "16": 318, "12": 943, "18": 53, "4": 132, "3": 65, "1": 15, "2": 20, "0": 2}, "20": {"11": 1533, "10": 1604, "12": 1422, "8": 1020, "9": 1123, "13": 969, "7": 623, "15": 241, "6": 297, "19": 246, "14": 601, "18": 60, "16": 77, "5": 115, "4": 40, "17": 18, "3": 10, "1": 1}, "844": {"7": 991, "8": 554, "19": 218, "11": 203, "4": 1607, "6": 1387, "5": 1621, "10": 287, "9": 405, "3": 991, "2": 526, "0": 272, "13": 105, "1": 319, "18": 89, "17": 20, "14": 247, "15": 24, "12": 127, "16": 7}, "853": {"19": 5567, "17": 974, "18": 3261, "16": 179, "15": 16, "14": 1, "13": 2}, "854": {"18": 5369, "16": 904, "17": 3160, "15": 176, "19": 373, "14": 12, "13": 5, "12": 1}, "846": {"3": 1456, "4": 2717, "9": 266, "5": 1835, "6": 1387, "8": 161, "17": 20, "19": 216, "2": 628, "10": 32, "7": 551, "18": 99, "1": 249, "0": 74, "14": 217, "13": 66, "12": 12, "11": 12, "16": 2}, "832": {"8": 903, "9": 631, "18": 87, "6": 1587, "10": 434, "5": 1480, "7": 1317, "3": 584, "4": 1058, "12": 238, "11": 348, "15": 39, "17": 19, "1": 217, "2": 323, "14": 263, "19": 191, "0": 69, "16": 17, "13": 195}, "1": {"0": 3883, "2": 1536, "1": 2641, "17": 33, "18": 100, "6": 30, "4": 237, "3": 665, "14": 209, "9": 221, "5": 100, "19": 170, "13": 93, "12": 13, "8": 49, "7": 16, "16": 3, "10": 1}, "822": {"1": 3148, "3": 1501, "2": 2560, "0": 844, "14": 220, "4": 606, "9": 233, "7": 39, "18": 96, "5": 299, "19": 175, "8": 57, "6": 100, "13": 70, "12": 14, "17": 27, "10": 3, "11": 4, "16": 4}, "815": {"14": 205, "5": 789, "3": 3259, "2": 1579, "1": 1549, "4": 1350, "8": 67, "19": 204, "9": 228, "13": 75, "6": 291, "0": 171, "18": 98, "7": 96, "12": 13, "11": 5, "17": 16, "16": 4, "10": 1}, "840": {"9": 1096, "12": 1010, "7": 1037, "8": 1514, "10": 1630, "14": 391, "11": 1311, "19": 246, "1": 2, "5": 285, "13": 543, "4": 102, "16": 27, "15": 110, "18": 53, "6": 605, "3": 20, "17": 16, "2": 2}, "4": {"12": 1419, "13": 915, "9": 1022, "11": 1563, "10": 1525, "8": 1086, "14": 558, "5": 166, "7": 707, "6": 332, "18": 52, "19": 225, "15": 269, "16": 76, "17": 25, "3": 14, "4": 43, "1": 1, "2": 2}, "830": {"2": 2385, "3": 418, "19": 163, "0": 4505, "14": 176, "1": 1633, "11": 3, "18": 101, "4": 162, "12": 22, "13": 81, "9": 208, "5": 41, "6": 5, "17": 22, "8": 67, "7": 6, "16": 2}, "817": {"5": 1702, "6": 1942, "4": 701, "10": 539, "13": 99, "8": 1128, "7": 1971, "11": 276, "18": 78, "9": 669, "17": 12, "12": 125, "3": 219, "19": 218, "14": 269, "1": 9, "2": 36, "16": 2, "15": 5}, "839": {"13": 1124, "11": 1683, "14": 644, "15": 341, "9": 939, "12": 1567, "16": 146, "6": 249, "10": 1436, "7": 505, "19": 238, "8": 875, "5": 112, "4": 37, "18": 70, "2": 3, "17": 27, "3": 4}, "849": {"17": 2829, "16": 3076, "12": 168, "15": 2343, "14": 763, "13": 453, "10": 11, "19": 262, "18": 57, "11": 36, "9": 2}, "847": {"10": 782, "14": 1524, "6": 70, "12": 1530, "8": 371, "15": 1030, "13": 1842, "19": 274, "9": 653, "11": 1180, "16": 484, "7": 173, "18": 48, "17": 7, "4": 4, "5": 27, "3": 1}}}