{
    "name": "Sakhir Grand Prix",
    "year": 2020,
    "drivers": {
        "822": {
            "name": "Valtteri Bottas",
            "constructor": "Mercedes",
            "color": "#00D2BE"
        },
        "847": {
            "name": "George Russell",
            "constructor": "Mercedes",
            "color": "#00D2BE"
        },
        "830": {
            "name": "Max Verstappen",
            "constructor": "Red Bull",
            "color": "#0600EF"
        },
        "844": {
            "name": "Charles Leclerc",
            "constructor": "Ferrari",
            "color": "#C00000"
        },
        "815": {
            "name": "Sergio P\u00e9rez",
            "constructor": "Racing Point",
            "color": "#F596C8"
        },
        "826": {
            "name": "Daniil Kvyat",
            "constructor": "AlphaTauri",
            "color": "#C8C8C8"
        },
        "817": {
            "name": "Daniel Ricciardo",
            "constructor": "Renault",
            "color": "#FFF500"
        },
        "832": {
            "name": "Carlos Sainz",
            "constructor": "McLaren",
            "color": "#FF8700"
        },
        "842": {
            "name": "Pierre Gasly",
            "constructor": "AlphaTauri",
            "color": "#C8C8C8"
        },
        "840": {
            "name": "Lance Stroll",
            "constructor": "Racing Point",
            "color": "#F596C8"
        },
        "839": {
            "name": "Esteban Ocon",
            "constructor": "Renault",
            "color": "#FFF500"
        },
        "848": {
            "name": "Alexander Albon",
            "constructor": "Red Bull",
            "color": "#0600EF"
        },
        "20": {
            "name": "Sebastian Vettel",
            "constructor": "Ferrari",
            "color": "#C00000"
        },
        "841": {
            "name": "Antonio Giovinazzi",
            "constructor": "Alfa Romeo",
            "color": "#960000"
        },
        "846": {
            "name": "Lando Norris",
            "constructor": "McLaren",
            "color": "#FF8700"
        },
        "825": {
            "name": "Kevin Magnussen",
            "constructor": "Haas F1 Team",
            "color": "#787878"
        },
        "849": {
            "name": "Nicholas Latifi",
            "constructor": "Williams",
            "color": "#0082FA"
        },
        "-2": {
            "name": "Jack Aitken",
            "constructor": "Williams",
            "color": "#0082FA"
        },
        "8": {
            "name": "Kimi R\u00e4ikk\u00f6nen",
            "constructor": "Alfa Romeo",
            "color": "#960000"
        },
        "-1": {
            "name": "Pietro Fittipaldi",
            "constructor": "Haas F1 Team",
            "color": "#787878"
        }
    },
    "order": [
        822,
        847,
        830,
        844,
        832,
        817,
        815,
        826,
        848,
        839,
        842,
        20,
        840,
        846,
        841,
        8,
        825,
        849,
        -2,
        -1
    ],
    "predictions": {
        "822": {
            "2": 724,
            "0": 5309,
            "ret": 922,
            "1": 2383,
            "3": 300,
            "7": 30,
            "4": 161,
            "6": 46,
            "5": 70,
            "9": 13,
            "8": 28,
            "10": 6,
            "12": 4,
            "11": 4
        },
        "847": {
            "1": 3807,
            "ret": 1856,
            "4": 197,
            "0": 2061,
            "2": 1332,
            "3": 435,
            "7": 45,
            "8": 41,
            "5": 120,
            "6": 69,
            "10": 7,
            "9": 18,
            "11": 7,
            "12": 5
        },
        "830": {
            "3": 1022,
            "5": 269,
            "1": 1686,
            "ret": 1747,
            "0": 1838,
            "8": 74,
            "4": 467,
            "6": 180,
            "2": 2504,
            "9": 48,
            "12": 2,
            "11": 15,
            "7": 110,
            "10": 35,
            "13": 2,
            "14": 1
        },
        "844": {
            "0": 401,
            "4": 1165,
            "1": 786,
            "ret": 1553,
            "5": 861,
            "2": 1601,
            "7": 417,
            "3": 1747,
            "6": 617,
            "10": 145,
            "9": 215,
            "12": 51,
            "13": 15,
            "8": 330,
            "11": 90,
            "15": 1,
            "14": 5
        },
        "815": {
            "6": 999,
            "2": 1039,
            "11": 190,
            "10": 333,
            "ret": 1007,
            "3": 1448,
            "4": 1376,
            "7": 801,
            "8": 581,
            "9": 454,
            "5": 1207,
            "17": 2,
            "12": 105,
            "1": 348,
            "0": 59,
            "15": 7,
            "13": 33,
            "14": 11
        },
        "826": {
            "9": 696,
            "1": 160,
            "5": 1194,
            "3": 957,
            "8": 796,
            "6": 1211,
            "14": 25,
            "4": 1113,
            "7": 1052,
            "ret": 1282,
            "11": 273,
            "2": 507,
            "10": 445,
            "13": 67,
            "12": 153,
            "0": 55,
            "16": 3,
            "15": 9,
            "17": 2
        },
        "817": {
            "5": 1164,
            "ret": 1730,
            "3": 1186,
            "4": 1374,
            "7": 800,
            "6": 968,
            "2": 816,
            "1": 316,
            "9": 374,
            "8": 556,
            "10": 281,
            "14": 17,
            "16": 3,
            "0": 109,
            "11": 182,
            "13": 27,
            "12": 88,
            "15": 8,
            "17": 1
        },
        "832": {
            "ret": 1683,
            "7": 706,
            "6": 914,
            "3": 1303,
            "2": 856,
            "1": 343,
            "4": 1307,
            "5": 1138,
            "8": 609,
            "10": 277,
            "13": 40,
            "9": 399,
            "11": 180,
            "12": 82,
            "0": 147,
            "15": 8,
            "14": 7,
            "17": 1
        },
        "842": {
            "10": 976,
            "3": 244,
            "9": 1219,
            "8": 1244,
            "5": 738,
            "ret": 1410,
            "12": 451,
            "14": 68,
            "7": 1117,
            "11": 727,
            "6": 903,
            "4": 505,
            "1": 27,
            "13": 219,
            "2": 85,
            "16": 14,
            "17": 10,
            "18": 4,
            "15": 35,
            "0": 4
        },
        "840": {
            "11": 835,
            "8": 944,
            "ret": 2644,
            "13": 247,
            "9": 1022,
            "7": 870,
            "5": 508,
            "15": 32,
            "2": 49,
            "6": 656,
            "10": 1015,
            "14": 101,
            "4": 319,
            "3": 171,
            "12": 562,
            "1": 7,
            "16": 13,
            "17": 4,
            "18": 1
        },
        "839": {
            "ret": 1764,
            "5": 760,
            "8": 1122,
            "7": 1045,
            "6": 956,
            "10": 937,
            "3": 297,
            "4": 553,
            "9": 1120,
            "11": 695,
            "12": 341,
            "14": 64,
            "1": 29,
            "15": 24,
            "13": 165,
            "2": 111,
            "0": 5,
            "16": 10,
            "17": 1,
            "18": 1
        },
        "848": {
            "7": 1118,
            "2": 244,
            "8": 1145,
            "10": 806,
            "ret": 1198,
            "4": 817,
            "6": 1056,
            "11": 512,
            "12": 335,
            "15": 23,
            "3": 557,
            "5": 961,
            "9": 952,
            "1": 75,
            "13": 128,
            "14": 55,
            "16": 4,
            "17": 5,
            "0": 8,
            "19": 1
        },
        "20": {
            "4": 463,
            "ret": 1223,
            "7": 958,
            "2": 101,
            "8": 1165,
            "11": 961,
            "9": 1202,
            "10": 1197,
            "5": 690,
            "6": 850,
            "12": 557,
            "3": 259,
            "13": 231,
            "15": 26,
            "14": 65,
            "0": 4,
            "16": 16,
            "1": 26,
            "19": 1,
            "17": 5
        },
        "841": {
            "8": 194,
            "10": 952,
            "16": 201,
            "14": 848,
            "12": 1794,
            "ret": 1805,
            "7": 89,
            "11": 1495,
            "13": 1537,
            "18": 34,
            "9": 513,
            "6": 39,
            "15": 353,
            "17": 110,
            "5": 21,
            "19": 9,
            "4": 5,
            "3": 1
        },
        "846": {
            "ret": 1061,
            "9": 1363,
            "6": 523,
            "12": 951,
            "8": 1050,
            "11": 1352,
            "7": 799,
            "10": 1531,
            "13": 457,
            "5": 298,
            "14": 180,
            "15": 89,
            "4": 178,
            "2": 31,
            "17": 14,
            "3": 73,
            "16": 34,
            "18": 7,
            "1": 7,
            "19": 2
        },
        "825": {
            "12": 1009,
            "ret": 1840,
            "15": 1376,
            "13": 1465,
            "14": 1665,
            "16": 912,
            "11": 622,
            "9": 102,
            "8": 30,
            "17": 477,
            "7": 14,
            "10": 275,
            "18": 184,
            "19": 25,
            "6": 3,
            "5": 1
        },
        "849": {
            "15": 1528,
            "13": 1291,
            "11": 452,
            "ret": 1938,
            "14": 1546,
            "12": 842,
            "18": 287,
            "16": 1135,
            "17": 651,
            "10": 190,
            "19": 47,
            "9": 66,
            "6": 3,
            "8": 16,
            "7": 8
        },
        "-2": {
            "14": 1608,
            "12": 660,
            "ret": 1219,
            "15": 1679,
            "11": 322,
            "13": 1104,
            "17": 1056,
            "16": 1582,
            "18": 477,
            "19": 101,
            "8": 8,
            "10": 137,
            "9": 46,
            "6": 1
        },
        "8": {
            "13": 1779,
            "11": 852,
            "16": 740,
            "10": 379,
            "14": 1610,
            "9": 147,
            "15": 1215,
            "ret": 1179,
            "17": 395,
            "12": 1430,
            "19": 29,
            "8": 60,
            "18": 160,
            "7": 20,
            "6": 5
        },
        "-1": {
            "ret": 1308,
            "14": 1430,
            "15": 1801,
            "16": 1705,
            "13": 956,
            "17": 1246,
            "12": 505,
            "18": 569,
            "11": 217,
            "9": 31,
            "10": 74,
            "19": 149,
            "8": 7,
            "6": 1,
            "7": 1
        }
    }
}